build_pip_package/__init__.py
build_pip_package/main.py
build_pip_package-2025.9.91807.dist-info/licenses/LICENSE
build_pip_package-2025.9.91807.dist-info/METADATA
build_pip_package-2025.9.91807.dist-info/WHEEL
build_pip_package-2025.9.91807.dist-info/top_level.txt
build_pip_package-2025.9.91807.dist-info/RECORD
