Metadata-Version: 2.4
Name: build_pip_package
Version: 2025.9.91807
Summary: A package for building pip packages using LLM7 and related tools
Home-page: https://github.com/chigwell/build_pip_package
Author: Eugene Evstafev
Author-email: Package Author <author@example.com>
License: MIT
Project-URL: Homepage, https://github.com/chigwell/build_pip_package
Project-URL: Repository, https://github.com/chigwell/build_pip_package.git
Project-URL: Issues, https://github.com/chigwell/build_pip_package/issues
Keywords: pip,package,build,llm7,langchain
Classifier: Development Status :: 3 - Alpha
Classifier: Intended Audience :: Developers
Classifier: License :: OSI Approved :: MIT License
Classifier: Operating System :: OS Independent
Classifier: Programming Language :: Python :: 3
Classifier: Programming Language :: Python :: 3.7
Classifier: Programming Language :: Python :: 3.8
Classifier: Programming Language :: Python :: 3.9
Classifier: Programming Language :: Python :: 3.10
Classifier: Programming Language :: Python :: 3.11
Requires-Python: >=3.7
License-File: LICENSE
Requires-Dist: py_llm7_code
Requires-Dist: setup_py_gen
Requires-Dist: readme_llm7_gen
Requires-Dist: langchain_llm7
Requires-Dist: langchain_core
Dynamic: author
Dynamic: home-page
Dynamic: license-file
Dynamic: requires-python
